cisco_support/__init__.py
cisco_support/auth.py
cisco_support/automated_software_distribution.py
cisco_support/bug.py
cisco_support/case.py
cisco_support/eox.py
cisco_support/product_information.py
cisco_support/serial_number.py
cisco_support/service_order_return.py
cisco_support/software_suggestion.py
cisco_support-0.5.2.dist-info/LICENSE
cisco_support-0.5.2.dist-info/METADATA
cisco_support-0.5.2.dist-info/WHEEL
cisco_support-0.5.2.dist-info/top_level.txt
cisco_support-0.5.2.dist-info/RECORD
