Metadata-Version: 2.1
Name: cisco_support
Version: 0.5.2
Summary: Python library to interact with Cisco Support APIs
License: MIT License
Project-URL: Homepage, https://github.com/rothdennis/cisco_support
Project-URL: Documentation, https://readthedocs.org
Project-URL: Repository, https://github.com/rothdennis/cisco_support.git
Project-URL: Issues, https://github.com/rothdennis/cisco_support/issues
Keywords: cisco
License-File: LICENSE
Requires-Dist: requests
